pictlogger/__init__.py
pictlogger/pictlogger.so
PictLogger-0.1.3.dist-info/LICENSE
PictLogger-0.1.3.dist-info/METADATA
PictLogger-0.1.3.dist-info/WHEEL
PictLogger-0.1.3.dist-info/top_level.txt
PictLogger-0.1.3.dist-info/RECORD
