Metadata-Version: 2.1
Name: PictLogger
Version: 0.1.3
Summary: Simple logger writen in c++
Author: Ilya Dudelzak
Author-email: Ilya Dudelzak <DIA070611@gmail.com>
Classifier: Programming Language :: Python :: 3
Classifier: License :: OSI Approved :: MIT License
Classifier: Operating System :: OS Independent
Requires-Python: >=3.7
License-File: LICENSE
